raytrace_torch/__init__.py
raytrace_torch-0.0.2.dist-info/METADATA
raytrace_torch-0.0.2.dist-info/WHEEL
raytrace_torch-0.0.2.dist-info/licenses/LICENSE
raytrace_torch-0.0.2.dist-info/RECORD
